src/__init__.py
src/cli.py
src/constants.py
src/db.py
src/helper.py
src/task.py
src/commands/__init__.py
src/commands/add.py
src/commands/complete.py
src/commands/delete.py
src/commands/edit.py
src/commands/helper.py
src/commands/list.py
src/commands/listall.py
src/commands/move.py
src/commands/reset.py
src/commands/update.py
todo_ksumit-0.0.4.dist-info/LICENSE
todo_ksumit-0.0.4.dist-info/METADATA
todo_ksumit-0.0.4.dist-info/WHEEL
todo_ksumit-0.0.4.dist-info/entry_points.txt
todo_ksumit-0.0.4.dist-info/top_level.txt
todo_ksumit-0.0.4.dist-info/RECORD
